yipy/__init__.py
yipy/api.py
yipy/config.py
yipy/yipy.py
yipy-1.0.0.dist-info/LICENSE
yipy-1.0.0.dist-info/METADATA
yipy-1.0.0.dist-info/WHEEL
yipy-1.0.0.dist-info/top_level.txt
yipy-1.0.0.dist-info/RECORD
