Metadata-Version: 2.1
Name: yipy
Version: 1.0.0
Summary: A python wraper for Yify's API.
Home-page: https://github.com/patillacode/yipy
Author: Patilla Code
Author-email: patillacode@gmail.com
License: MIT
Keywords: yify,api,python
Platform: UNKNOWN
Classifier: Intended Audience :: Developers
Classifier: Topic :: Utilities
Classifier: License :: Public Domain
Classifier: Natural Language :: English
Classifier: Operating System :: OS Independent
Classifier: Programming Language :: Python :: 3.7
Requires-Dist: requests
